_sts.abi3.so
sts.py
sts_pylib-0.0.5.dist-info/WHEEL
sts_pylib-0.0.5.dist-info/LICENSE
sts_pylib-0.0.5.dist-info/top_level.txt
sts_pylib-0.0.5.dist-info/RECORD
sts_pylib-0.0.5.dist-info/METADATA
