Metadata-Version: 2.1
Name: sts-pylib
Version: 0.0.5
Summary: Functional interface to the NIST randomness tests
Home-page: https://github.com/Honno/sts-pylib
Author: Matthew Barber
Author-email: quitesimplymatt@gmail.com
License: UNKNOWN
Project-URL: Documentation, https://sts-pylib.readthedocs.io/
Project-URL: Issue Tracker, https://github.com/Honno/sts-pylib/issues
Keywords: rng,prng,randomness,nist,sts,statistics,tests,randomness-testing,cryptography,data-science
Platform: UNKNOWN
Classifier: Development Status :: 3 - Alpha
Classifier: Intended Audience :: Developers
Classifier: Operating System :: Unix
Classifier: Operating System :: POSIX
Classifier: Operating System :: MacOS
Classifier: Operating System :: Microsoft :: Windows
Classifier: Programming Language :: Python
Classifier: Programming Language :: Python :: 3
Classifier: Programming Language :: Python :: 3.6
Classifier: Programming Language :: Python :: 3.7
Classifier: Programming Language :: Python :: 3.8
Classifier: Programming Language :: Python :: Implementation :: CPython
Classifier: License :: OSI Approved :: BSD License
Classifier: Topic :: Security :: Cryptography
Classifier: Topic :: Software Development :: Libraries
Requires-Dist: cffi (>=1.0.0)
